{  "response": {  "version":"0.1",  "termsofService":"http://www.wunderground.com/weather/api/d/terms.html",  "features": {  "history": 1  }	}		,	"history": {		"date": {		"pretty": "January 23, 2012",		"year": "2012",		"mon": "01",		"mday": "23",		"hour": "12",		"min": "00",		"tzname": "America/Chicago"		},		"utcdate": {		"pretty": "January 23, 2012",		"year": "2012",		"mon": "01",		"mday": "23",		"hour": "18",		"min": "00",		"tzname": "UTC"		},		"observations": [		{		"date": {		"pretty": "12:53 AM CST on January 23, 2012",		"year": "2012",		"mon": "01",		"mday": "23",		"hour": "00",		"min": "53",		"tzname": "America/Chicago"		},		"utcdate": {		"pretty": "6:53 AM GMT on January 23, 2012",		"year": "2012",		"mon": "01",		"mday": "23",		"hour": "06",		"min": "53",		"tzname": "UTC"		},		"tempm":"8.9", "tempi":"48.0","dewptm":"5.6", "dewpti":"42.1","hum":"80","wspdm":"11.1", "wspdi":"6.9","wgustm":"-9999.0", "wgusti":"-9999.0","wdird":"320","wdire":"NW","vism":"16.1", "visi":"10.0","pressurem":"1014.6", "pressurei":"29.96","windchillm":"-999", "windchilli":"-999","heatindexm":"-9999", "heatindexi":"-9999","precipm":"-9999.00", "precipi":"-9999.00","conds":"Scattered Clouds","icon":"partlycloudy","fog":"0","rain":"0","snow":"0","hail":"0","thunder":"0","tornado":"0","metar":"METAR KAUS 230653Z 32006KT 10SM SCT028 09/06 A2997 RMK AO2 SLP146 T00890056" },		{		"date": {		"pretty": "1:53 AM CST on January 23, 2012",		"year": "2012",		"mon": "01",		"mday": "23",		"hour": "01",		"min": "53",		"tzname": "America/Chicago"		},		"utcdate": {		"pretty": "7:53 AM GMT on January 23, 2012",		"year": "2012",		"mon": "01",		"mday": "23",		"hour": "07",		"min": "53",		"tzname": "UTC"		},		"tempm":"11.1", "tempi":"52.0","dewptm":"2.8", "dewpti":"37.0","hum":"57","wspdm":"11.1", "wspdi":"6.9","wgustm":"-9999.0", "wgusti":"-9999.0","wdird":"340","wdire":"NNW","vism":"16.1", "visi":"10.0","pressurem":"1015.2", "pressurei":"29.98","windchillm":"-999", "windchilli":"-999","heatindexm":"-9999", "heatindexi":"-9999","precipm":"-9999.00", "precipi":"-9999.00","conds":"Scattered Clouds","icon":"partlycloudy","fog":"0","rain":"0","snow":"0","hail":"0","thunder":"0","tornado":"0","metar":"METAR KAUS 230753Z 34006KT 10SM SCT031 11/03 A2999 RMK AO2 SLP152 T01110028" },		{		"date": {		"pretty": "2:53 AM CST on January 23, 2012",		"year": "2012",		"mon": "01",		"mday": "23",		"hour": "02",		"min": "53",		"tzname": "America/Chicago"		},		"utcdate": {		"pretty": "8:53 AM GMT on January 23, 2012",		"year": "2012",		"mon": "01",		"mday": "23",		"hour": "08",		"min": "53",		"tzname": "UTC"		},		"tempm":"9.4", "tempi":"48.9","dewptm":"2.8", "dewpti":"37.0","hum":"64","wspdm":"11.1", "wspdi":"6.9","wgustm":"-9999.0", "wgusti":"-9999.0","wdird":"360","wdire":"North","vism":"16.1", "visi":"10.0","pressurem":"1016.0", "pressurei":"30.01","windchillm":"-999", "windchilli":"-999","heatindexm":"-9999", "heatindexi":"-9999","precipm":"-9999.00", "precipi":"-9999.00","conds":"Scattered Clouds","icon":"partlycloudy","fog":"0","rain":"0","snow":"0","hail":"0","thunder":"0","tornado":"0","metar":"METAR KAUS 230853Z 36006KT 10SM SCT037 09/03 A3001 RMK AO2 SLP160 T00940028 53021" },		{		"date": {		"pretty": "3:53 AM CST on January 23, 2012",		"year": "2012",		"mon": "01",		"mday": "23",		"hour": "03",		"min": "53",		"tzname": "America/Chicago"		},		"utcdate": {		"pretty": "9:53 AM GMT on January 23, 2012",		"year": "2012",		"mon": "01",		"mday": "23",		"hour": "09",		"min": "53",		"tzname": "UTC"		},		"tempm":"6.1", "tempi":"43.0","dewptm":"2.8", "dewpti":"37.0","hum":"80","wspdm":"14.8", "wspdi":"9.2","wgustm":"-9999.0", "wgusti":"-9999.0","wdird":"10","wdire":"North","vism":"16.1", "visi":"10.0","pressurem":"1016.5", "pressurei":"30.02","windchillm":"3.2", "windchilli":"37.7","heatindexm":"-9999", "heatindexi":"-9999","precipm":"-9999.00", "precipi":"-9999.00","conds":"Partly Cloudy","icon":"partlycloudy","fog":"0","rain":"0","snow":"0","hail":"0","thunder":"0","tornado":"0","metar":"METAR KAUS 230953Z 01008KT 10SM FEW040 06/03 A3002 RMK AO2 SLP165 T00610028" },		{		"date": {		"pretty": "4:53 AM CST on January 23, 2012",		"year": "2012",		"mon": "01",		"mday": "23",		"hour": "04",		"min": "53",		"tzname": "America/Chicago"		},		"utcdate": {		"pretty": "10:53 AM GMT on January 23, 2012",		"year": "2012",		"mon": "01",		"mday": "23",		"hour": "10",		"min": "53",		"tzname": "UTC"		},		"tempm":"8.3", "tempi":"46.9","dewptm":"3.9", "dewpti":"39.0","hum":"74","wspdm":"14.8", "wspdi":"9.2","wgustm":"-9999.0", "wgusti":"-9999.0","wdird":"360","wdire":"North","vism":"16.1", "visi":"10.0","pressurem":"1016.8", "pressurei":"30.03","windchillm":"-999", "windchilli":"-999","heatindexm":"-9999", "heatindexi":"-9999","precipm":"-9999.00", "precipi":"-9999.00","conds":"Clear","icon":"clear","fog":"0","rain":"0","snow":"0","hail":"0","thunder":"0","tornado":"0","metar":"METAR KAUS 231053Z 36008KT 10SM CLR 08/04 A3003 RMK AO2 SLP168 T00830039" },		{		"date": {		"pretty": "5:53 AM CST on January 23, 2012",		"year": "2012",		"mon": "01",		"mday": "23",		"hour": "05",		"min": "53",		"tzname": "America/Chicago"		},		"utcdate": {		"pretty": "11:53 AM GMT on January 23, 2012",		"year": "2012",		"mon": "01",		"mday": "23",		"hour": "11",		"min": "53",		"tzname": "UTC"		},		"tempm":"5.6", "tempi":"42.1","dewptm":"2.8", "dewpti":"37.0","hum":"82","wspdm":"7.4", "wspdi":"4.6","wgustm":"-9999.0", "wgusti":"-9999.0","wdird":"10","wdire":"North","vism":"16.1", "visi":"10.0","pressurem":"1017.9", "pressurei":"30.06","windchillm":"4.0", "windchilli":"39.2","heatindexm":"-9999", "heatindexi":"-9999","precipm":"-9999.00", "precipi":"-9999.00","conds":"Clear","icon":"clear","fog":"0","rain":"0","snow":"0","hail":"0","thunder":"0","tornado":"0","metar":"METAR KAUS 231153Z 01004KT 10SM CLR 06/03 A3006 RMK AO2 SLP179 T00560028 10128 20056 53016" },		{		"date": {		"pretty": "6:53 AM CST on January 23, 2012",		"year": "2012",		"mon": "01",		"mday": "23",		"hour": "06",		"min": "53",		"tzname": "America/Chicago"		},		"utcdate": {		"pretty": "12:53 PM GMT on January 23, 2012",		"year": "2012",		"mon": "01",		"mday": "23",		"hour": "12",		"min": "53",		"tzname": "UTC"		},		"tempm":"7.2", "tempi":"45.0","dewptm":"2.8", "dewpti":"37.0","hum":"74","wspdm":"9.3", "wspdi":"5.8","wgustm":"-9999.0", "wgusti":"-9999.0","wdird":"360","wdire":"North","vism":"16.1", "visi":"10.0","pressurem":"1018.5", "pressurei":"30.08","windchillm":"5.5", "windchilli":"41.8","heatindexm":"-9999", "heatindexi":"-9999","precipm":"-9999.00", "precipi":"-9999.00","conds":"Scattered Clouds","icon":"partlycloudy","fog":"0","rain":"0","snow":"0","hail":"0","thunder":"0","tornado":"0","metar":"METAR KAUS 231253Z 36005KT 10SM SCT150 07/03 A3008 RMK AO2 SLP185 T00720028" },		{		"date": {		"pretty": "7:53 AM CST on January 23, 2012",		"year": "2012",		"mon": "01",		"mday": "23",		"hour": "07",		"min": "53",		"tzname": "America/Chicago"		},		"utcdate": {		"pretty": "1:53 PM GMT on January 23, 2012",		"year": "2012",		"mon": "01",		"mday": "23",		"hour": "13",		"min": "53",		"tzname": "UTC"		},		"tempm":"6.0", "tempi":"42.8","dewptm":"3.0", "dewpti":"37.4","hum":"81","wspdm":"9.3", "wspdi":"5.8","wgustm":"-9999.0", "wgusti":"-9999.0","wdird":"10","wdire":"North","vism":"16.1", "visi":"10.0","pressurem":"1018.8", "pressurei":"30.09","windchillm":"4.0", "windchilli":"39.3","heatindexm":"-9999", "heatindexi":"-9999","precipm":"-9999.00", "precipi":"-9999.00","conds":"Mostly Cloudy","icon":"mostlycloudy","fog":"0","rain":"0","snow":"0","hail":"0","thunder":"0","tornado":"0","metar":"METAR KAUS 231353Z 01005KT 10SM SCT200 BKN250 06/03 A3009" },		{		"date": {		"pretty": "8:53 AM CST on January 23, 2012",		"year": "2012",		"mon": "01",		"mday": "23",		"hour": "08",		"min": "53",		"tzname": "America/Chicago"		},		"utcdate": {		"pretty": "2:53 PM GMT on January 23, 2012",		"year": "2012",		"mon": "01",		"mday": "23",		"hour": "14",		"min": "53",		"tzname": "UTC"		},		"tempm":"10.0", "tempi":"50.0","dewptm":"4.4", "dewpti":"39.9","hum":"68","wspdm":"18.5", "wspdi":"11.5","wgustm":"-9999.0", "wgusti":"-9999.0","wdird":"360","wdire":"North","vism":"16.1", "visi":"10.0","pressurem":"1020.0", "pressurei":"30.12","windchillm":"-999", "windchilli":"-999","heatindexm":"-9999", "heatindexi":"-9999","precipm":"-9999.00", "precipi":"-9999.00","conds":"Mostly Cloudy","icon":"mostlycloudy","fog":"0","rain":"0","snow":"0","hail":"0","thunder":"0","tornado":"0","metar":"METAR KAUS 231453Z 36010KT 10SM SCT200 BKN250 10/04 A3012 RMK AO2 SLP200 T01000044 53020" },		{		"date": {		"pretty": "9:53 AM CST on January 23, 2012",		"year": "2012",		"mon": "01",		"mday": "23",		"hour": "09",		"min": "53",		"tzname": "America/Chicago"		},		"utcdate": {		"pretty": "3:53 PM GMT on January 23, 2012",		"year": "2012",		"mon": "01",		"mday": "23",		"hour": "15",		"min": "53",		"tzname": "UTC"		},		"tempm":"11.7", "tempi":"53.1","dewptm":"3.9", "dewpti":"39.0","hum":"59","wspdm":"14.8", "wspdi":"9.2","wgustm":"-9999.0", "wgusti":"-9999.0","wdird":"20","wdire":"NNE","vism":"16.1", "visi":"10.0","pressurem":"1021.0", "pressurei":"30.15","windchillm":"-999", "windchilli":"-999","heatindexm":"-9999", "heatindexi":"-9999","precipm":"-9999.00", "precipi":"-9999.00","conds":"Mostly Cloudy","icon":"mostlycloudy","fog":"0","rain":"0","snow":"0","hail":"0","thunder":"0","tornado":"0","metar":"METAR KAUS 231553Z 02008KT 10SM SCT200 BKN250 12/04 A3015 RMK AO2 SLP210 T01170039" },		{		"date": {		"pretty": "10:53 AM CST on January 23, 2012",		"year": "2012",		"mon": "01",		"mday": "23",		"hour": "10",		"min": "53",		"tzname": "America/Chicago"		},		"utcdate": {		"pretty": "4:53 PM GMT on January 23, 2012",		"year": "2012",		"mon": "01",		"mday": "23",		"hour": "16",		"min": "53",		"tzname": "UTC"		},		"tempm":"13.0", "tempi":"55.4","dewptm":"3.0", "dewpti":"37.4","hum":"51","wspdm":"18.5", "wspdi":"11.5","wgustm":"-9999.0", "wgusti":"-9999.0","wdird":"20","wdire":"NNE","vism":"16.1", "visi":"10.0","pressurem":"1020.9", "pressurei":"30.15","windchillm":"-999", "windchilli":"-999","heatindexm":"-9999", "heatindexi":"-9999","precipm":"-9999.00", "precipi":"-9999.00","conds":"Mostly Cloudy","icon":"mostlycloudy","fog":"0","rain":"0","snow":"0","hail":"0","thunder":"0","tornado":"0","metar":"METAR KAUS 231653Z 02010KT 10SM SCT200 BKN250 13/03 A3015" },		{		"date": {		"pretty": "11:53 AM CST on January 23, 2012",		"year": "2012",		"mon": "01",		"mday": "23",		"hour": "11",		"min": "53",		"tzname": "America/Chicago"		},		"utcdate": {		"pretty": "5:53 PM GMT on January 23, 2012",		"year": "2012",		"mon": "01",		"mday": "23",		"hour": "17",		"min": "53",		"tzname": "UTC"		},		"tempm":"15.0", "tempi":"59.0","dewptm":"2.8", "dewpti":"37.0","hum":"44","wspdm":"16.7", "wspdi":"10.4","wgustm":"-9999.0", "wgusti":"-9999.0","wdird":"20","wdire":"NNE","vism":"16.1", "visi":"10.0","pressurem":"1020.0", "pressurei":"30.12","windchillm":"-999", "windchilli":"-999","heatindexm":"-9999", "heatindexi":"-9999","precipm":"-9999.00", "precipi":"-9999.00","conds":"Mostly Cloudy","icon":"mostlycloudy","fog":"0","rain":"0","snow":"0","hail":"0","thunder":"0","tornado":"0","metar":"METAR KAUS 231753Z 02009KT 10SM SCT200 BKN250 15/03 A3012 RMK AO2 SLP200 T01500028 10150 20050 50001" },		{		"date": {		"pretty": "12:53 PM CST on January 23, 2012",		"year": "2012",		"mon": "01",		"mday": "23",		"hour": "12",		"min": "53",		"tzname": "America/Chicago"		},		"utcdate": {		"pretty": "6:53 PM GMT on January 23, 2012",		"year": "2012",		"mon": "01",		"mday": "23",		"hour": "18",		"min": "53",		"tzname": "UTC"		},		"tempm":"16.1", "tempi":"61.0","dewptm":"2.8", "dewpti":"37.0","hum":"41","wspdm":"14.8", "wspdi":"9.2","wgustm":"-9999.0", "wgusti":"-9999.0","wdird":"40","wdire":"NE","vism":"16.1", "visi":"10.0","pressurem":"1019.0", "pressurei":"30.09","windchillm":"-999", "windchilli":"-999","heatindexm":"-9999", "heatindexi":"-9999","precipm":"-9999.00", "precipi":"-9999.00","conds":"Mostly Cloudy","icon":"mostlycloudy","fog":"0","rain":"0","snow":"0","hail":"0","thunder":"0","tornado":"0","metar":"METAR KAUS 231853Z 04008KT 10SM SCT200 BKN250 16/03 A3009 RMK AO2 SLP190 T01610028" },		{		"date": {		"pretty": "1:53 PM CST on January 23, 2012",		"year": "2012",		"mon": "01",		"mday": "23",		"hour": "13",		"min": "53",		"tzname": "America/Chicago"		},		"utcdate": {		"pretty": "7:53 PM GMT on January 23, 2012",		"year": "2012",		"mon": "01",		"mday": "23",		"hour": "19",		"min": "53",		"tzname": "UTC"		},		"tempm":"17.2", "tempi":"63.0","dewptm":"2.8", "dewpti":"37.0","hum":"38","wspdm":"13.0", "wspdi":"8.1","wgustm":"-9999.0", "wgusti":"-9999.0","wdird":"40","wdire":"NE","vism":"16.1", "visi":"10.0","pressurem":"1017.5", "pressurei":"30.05","windchillm":"-999", "windchilli":"-999","heatindexm":"-9999", "heatindexi":"-9999","precipm":"-9999.00", "precipi":"-9999.00","conds":"Mostly Cloudy","icon":"mostlycloudy","fog":"0","rain":"0","snow":"0","hail":"0","thunder":"0","tornado":"0","metar":"METAR KAUS 231953Z 04007KT 10SM SCT250 BKN300 17/03 A3005 RMK AO2 SLP175 T01720028" },		{		"date": {		"pretty": "2:53 PM CST on January 23, 2012",		"year": "2012",		"mon": "01",		"mday": "23",		"hour": "14",		"min": "53",		"tzname": "America/Chicago"		},		"utcdate": {		"pretty": "8:53 PM GMT on January 23, 2012",		"year": "2012",		"mon": "01",		"mday": "23",		"hour": "20",		"min": "53",		"tzname": "UTC"		},		"tempm":"18.9", "tempi":"66.0","dewptm":"3.3", "dewpti":"37.9","hum":"36","wspdm":"14.8", "wspdi":"9.2","wgustm":"-9999.0", "wgusti":"-9999.0","wdird":"30","wdire":"NNE","vism":"16.1", "visi":"10.0","pressurem":"1016.4", "pressurei":"30.02","windchillm":"-999", "windchilli":"-999","heatindexm":"-9999", "heatindexi":"-9999","precipm":"-9999.00", "precipi":"-9999.00","conds":"Mostly Cloudy","icon":"mostlycloudy","fog":"0","rain":"0","snow":"0","hail":"0","thunder":"0","tornado":"0","metar":"METAR KAUS 232053Z 03008KT 10SM SCT250 BKN300 19/03 A3002 RMK AO2 SLP164 T01890033 57034" },		{		"date": {		"pretty": "3:53 PM CST on January 23, 2012",		"year": "2012",		"mon": "01",		"mday": "23",		"hour": "15",		"min": "53",		"tzname": "America/Chicago"		},		"utcdate": {		"pretty": "9:53 PM GMT on January 23, 2012",		"year": "2012",		"mon": "01",		"mday": "23",		"hour": "21",		"min": "53",		"tzname": "UTC"		},		"tempm":"18.9", "tempi":"66.0","dewptm":"3.3", "dewpti":"37.9","hum":"36","wspdm":"13.0", "wspdi":"8.1","wgustm":"-9999.0", "wgusti":"-9999.0","wdird":"40","wdire":"NE","vism":"16.1", "visi":"10.0","pressurem":"1016.1", "pressurei":"30.01","windchillm":"-999", "windchilli":"-999","heatindexm":"-9999", "heatindexi":"-9999","precipm":"-9999.00", "precipi":"-9999.00","conds":"Mostly Cloudy","icon":"mostlycloudy","fog":"0","rain":"0","snow":"0","hail":"0","thunder":"0","tornado":"0","metar":"METAR KAUS 232153Z 04007KT 10SM FEW200 SCT250 BKN300 19/03 A3001 RMK AO2 SLP161 T01890033" },		{		"date": {		"pretty": "4:53 PM CST on January 23, 2012",		"year": "2012",		"mon": "01",		"mday": "23",		"hour": "16",		"min": "53",		"tzname": "America/Chicago"		},		"utcdate": {		"pretty": "10:53 PM GMT on January 23, 2012",		"year": "2012",		"mon": "01",		"mday": "23",		"hour": "22",		"min": "53",		"tzname": "UTC"		},		"tempm":"18.3", "tempi":"64.9","dewptm":"3.3", "dewpti":"37.9","hum":"37","wspdm":"13.0", "wspdi":"8.1","wgustm":"-9999.0", "wgusti":"-9999.0","wdird":"60","wdire":"ENE","vism":"16.1", "visi":"10.0","pressurem":"1015.7", "pressurei":"30.00","windchillm":"-999", "windchilli":"-999","heatindexm":"-9999", "heatindexi":"-9999","precipm":"-9999.00", "precipi":"-9999.00","conds":"Scattered Clouds","icon":"partlycloudy","fog":"0","rain":"0","snow":"0","hail":"0","thunder":"0","tornado":"0","metar":"METAR KAUS 232253Z 06007KT 10SM FEW200 SCT250 18/03 A3000 RMK AO2 SLP157 T01830033" },		{		"date": {		"pretty": "5:53 PM CST on January 23, 2012",		"year": "2012",		"mon": "01",		"mday": "23",		"hour": "17",		"min": "53",		"tzname": "America/Chicago"		},		"utcdate": {		"pretty": "11:53 PM GMT on January 23, 2012",		"year": "2012",		"mon": "01",		"mday": "23",		"hour": "23",		"min": "53",		"tzname": "UTC"		},		"tempm":"15.6", "tempi":"60.1","dewptm":"3.9", "dewpti":"39.0","hum":"46","wspdm":"11.1", "wspdi":"6.9","wgustm":"-9999.0", "wgusti":"-9999.0","wdird":"40","wdire":"NE","vism":"16.1", "visi":"10.0","pressurem":"1016.0", "pressurei":"30.01","windchillm":"-999", "windchilli":"-999","heatindexm":"-9999", "heatindexi":"-9999","precipm":"-9999.00", "precipi":"-9999.00","conds":"Scattered Clouds","icon":"partlycloudy","fog":"0","rain":"0","snow":"0","hail":"0","thunder":"0","tornado":"0","metar":"METAR KAUS 232353Z 04006KT 10SM FEW200 SCT250 16/04 A3000 RMK AO2 SLP160 T01560039 10189 20144 55007" },		{		"date": {		"pretty": "6:53 PM CST on January 23, 2012",		"year": "2012",		"mon": "01",		"mday": "23",		"hour": "18",		"min": "53",		"tzname": "America/Chicago"		},		"utcdate": {		"pretty": "12:53 AM GMT on January 24, 2012",		"year": "2012",		"mon": "01",		"mday": "24",		"hour": "00",		"min": "53",		"tzname": "UTC"		},		"tempm":"8.9", "tempi":"48.0","dewptm":"3.3", "dewpti":"37.9","hum":"68","wspdm":"5.6", "wspdi":"3.5","wgustm":"-9999.0", "wgusti":"-9999.0","wdird":"20","wdire":"NNE","vism":"16.1", "visi":"10.0","pressurem":"1016.6", "pressurei":"30.02","windchillm":"-999", "windchilli":"-999","heatindexm":"-9999", "heatindexi":"-9999","precipm":"-9999.00", "precipi":"-9999.00","conds":"Scattered Clouds","icon":"partlycloudy","fog":"0","rain":"0","snow":"0","hail":"0","thunder":"0","tornado":"0","metar":"METAR KAUS 240053Z 02003KT 10SM FEW200 SCT250 09/03 A3001 RMK AO2 SLP166 T00890033" },		{		"date": {		"pretty": "7:53 PM CST on January 23, 2012",		"year": "2012",		"mon": "01",		"mday": "23",		"hour": "19",		"min": "53",		"tzname": "America/Chicago"		},		"utcdate": {		"pretty": "1:53 AM GMT on January 24, 2012",		"year": "2012",		"mon": "01",		"mday": "24",		"hour": "01",		"min": "53",		"tzname": "UTC"		},		"tempm":"8.9", "tempi":"48.0","dewptm":"3.3", "dewpti":"37.9","hum":"68","wspdm":"0.0", "wspdi":"0.0","wgustm":"-9999.0", "wgusti":"-9999.0","wdird":"0","wdire":"North","vism":"16.1", "visi":"10.0","pressurem":"1017.0", "pressurei":"30.04","windchillm":"-999", "windchilli":"-999","heatindexm":"-9999", "heatindexi":"-9999","precipm":"-9999.00", "precipi":"-9999.00","conds":"Partly Cloudy","icon":"partlycloudy","fog":"0","rain":"0","snow":"0","hail":"0","thunder":"0","tornado":"0","metar":"METAR KAUS 240153Z 00000KT 10SM FEW250 09/03 A3002 RMK AO2 SLP170 T00890033" },		{		"date": {		"pretty": "8:53 PM CST on January 23, 2012",		"year": "2012",		"mon": "01",		"mday": "23",		"hour": "20",		"min": "53",		"tzname": "America/Chicago"		},		"utcdate": {		"pretty": "2:53 AM GMT on January 24, 2012",		"year": "2012",		"mon": "01",		"mday": "24",		"hour": "02",		"min": "53",		"tzname": "UTC"		},		"tempm":"8.9", "tempi":"48.0","dewptm":"3.9", "dewpti":"39.0","hum":"71","wspdm":"0.0", "wspdi":"0.0","wgustm":"-9999.0", "wgusti":"-9999.0","wdird":"0","wdire":"North","vism":"16.1", "visi":"10.0","pressurem":"1017.0", "pressurei":"30.04","windchillm":"-999", "windchilli":"-999","heatindexm":"-9999", "heatindexi":"-9999","precipm":"-9999.00", "precipi":"-9999.00","conds":"Partly Cloudy","icon":"partlycloudy","fog":"0","rain":"0","snow":"0","hail":"0","thunder":"0","tornado":"0","metar":"METAR KAUS 240253Z 00000KT 10SM FEW250 09/04 A3003 RMK AO2 SLP170 T00890039 51009" },		{		"date": {		"pretty": "9:53 PM CST on January 23, 2012",		"year": "2012",		"mon": "01",		"mday": "23",		"hour": "21",		"min": "53",		"tzname": "America/Chicago"		},		"utcdate": {		"pretty": "3:53 AM GMT on January 24, 2012",		"year": "2012",		"mon": "01",		"mday": "24",		"hour": "03",		"min": "53",		"tzname": "UTC"		},		"tempm":"6.1", "tempi":"43.0","dewptm":"3.3", "dewpti":"37.9","hum":"82","wspdm":"0.0", "wspdi":"0.0","wgustm":"-9999.0", "wgusti":"-9999.0","wdird":"0","wdire":"North","vism":"16.1", "visi":"10.0","pressurem":"1017.3", "pressurei":"30.04","windchillm":"-999", "windchilli":"-999","heatindexm":"-9999", "heatindexi":"-9999","precipm":"-9999.00", "precipi":"-9999.00","conds":"Partly Cloudy","icon":"partlycloudy","fog":"0","rain":"0","snow":"0","hail":"0","thunder":"0","tornado":"0","metar":"METAR KAUS 240353Z 00000KT 10SM FEW200 06/03 A3003 RMK AO2 SLP173 T00610033" },		{		"date": {		"pretty": "10:53 PM CST on January 23, 2012",		"year": "2012",		"mon": "01",		"mday": "23",		"hour": "22",		"min": "53",		"tzname": "America/Chicago"		},		"utcdate": {		"pretty": "4:53 AM GMT on January 24, 2012",		"year": "2012",		"mon": "01",		"mday": "24",		"hour": "04",		"min": "53",		"tzname": "UTC"		},		"tempm":"5.6", "tempi":"42.1","dewptm":"3.3", "dewpti":"37.9","hum":"85","wspdm":"0.0", "wspdi":"0.0","wgustm":"-9999.0", "wgusti":"-9999.0","wdird":"0","wdire":"North","vism":"16.1", "visi":"10.0","pressurem":"1017.2", "pressurei":"30.04","windchillm":"-999", "windchilli":"-999","heatindexm":"-9999", "heatindexi":"-9999","precipm":"-9999.00", "precipi":"-9999.00","conds":"Partly Cloudy","icon":"partlycloudy","fog":"0","rain":"0","snow":"0","hail":"0","thunder":"0","tornado":"0","metar":"METAR KAUS 240453Z 00000KT 10SM FEW034 06/03 A3003 RMK AO2 SLP172 T00560033" },		{		"date": {		"pretty": "11:53 PM CST on January 23, 2012",		"year": "2012",		"mon": "01",		"mday": "23",		"hour": "23",		"min": "53",		"tzname": "America/Chicago"		},		"utcdate": {		"pretty": "5:53 AM GMT on January 24, 2012",		"year": "2012",		"mon": "01",		"mday": "24",		"hour": "05",		"min": "53",		"tzname": "UTC"		},		"tempm":"5.0", "tempi":"41.0","dewptm":"3.3", "dewpti":"37.9","hum":"89","wspdm":"0.0", "wspdi":"0.0","wgustm":"-9999.0", "wgusti":"-9999.0","wdird":"0","wdire":"North","vism":"16.1", "visi":"10.0","pressurem":"1016.8", "pressurei":"30.03","windchillm":"-999", "windchilli":"-999","heatindexm":"-9999", "heatindexi":"-9999","precipm":"-9999.00", "precipi":"-9999.00","conds":"Clear","icon":"clear","fog":"0","rain":"0","snow":"0","hail":"0","thunder":"0","tornado":"0","metar":"METAR KAUS 240553Z 00000KT 10SM CLR 05/03 A3002 RMK AO2 SLP168 T00500033 10156 20044 401890044 58002" }		],		"dailysummary": [		{ "date": {		"pretty": "12:00 PM CST on January 23, 2012",		"year": "2012",		"mon": "01",		"mday": "23",		"hour": "12",		"min": "00",		"tzname": "America/Chicago"		},		"fog":"0","rain":"0","snow":"0","snowfallm":"0.00", "snowfalli":"0.00","monthtodatesnowfallm":"0.00", "monthtodatesnowfalli":"0.00","since1julsnowfallm":"0.00", "since1julsnowfalli":"0.00","snowdepthm":"0.00", "snowdepthi":"0.00","hail":"0","thunder":"0","tornado":"0","meantempm":"12", "meantempi":"53","meandewptm":"3", "meandewpti":"38","meanpressurem":"1017", "meanpressurei":"30.05","meanwindspdm":"10", "meanwindspdi":"6","meanwdire":"","meanwdird":"16","meanvism":"16", "meanvisi":"10","humidity":"","maxtempm":"19", "maxtempi":"66","mintempm":"4", "mintempi":"40","maxhumidity":"100","minhumidity":"34","maxdewptm":"6", "maxdewpti":"42","mindewptm":"3", "mindewpti":"37","maxpressurem":"1021", "maxpressurei":"30.15","minpressurem":"1014", "minpressurei":"29.96","maxwspdm":"23", "maxwspdi":"14","minwspdm":"0", "minwspdi":"0","maxvism":"16", "maxvisi":"10","minvism":"16", "minvisi":"10","gdegreedays":"4","heatingdegreedays":"12","coolingdegreedays":"0","precipm":"0.00", "precipi":"0.00","precipsource":"","heatingdegreedaysnormal":"16","monthtodateheatingdegreedays":"296","monthtodateheatingdegreedaysnormal":"368","since1sepheatingdegreedays":"","since1sepheatingdegreedaysnormal":"","since1julheatingdegreedays":"986","since1julheatingdegreedaysnormal":"1115","coolingdegreedaysnormal":"0","monthtodatecoolingdegreedays":"3","monthtodatecoolingdegreedaysnormal":"0","since1sepcoolingdegreedays":"","since1sepcoolingdegreedaysnormal":"","since1jancoolingdegreedays":"3","since1jancoolingdegreedaysnormal":"0" }		]	}}